setup_server.py
common/__init__.py
common/decors.py
common/descriptrs.py
common/metaclasses.py
common/utils.py
common/variables.py
logs/__init__.py
logs/config/__init__.py
logs/config/config_log_server.py
logs/log-files/__init__.py
server/__init__.py
server/core.py
server/history_window.py
server/main_window.py
server/new_user.py
server/remove_user.py
server/server_db.py
server/settings_window.py
serverapp.egg-info/PKG-INFO
serverapp.egg-info/SOURCES.txt
serverapp.egg-info/dependency_links.txt
serverapp.egg-info/requires.txt
serverapp.egg-info/top_level.txt